<annotation>
	<folder>train</folder>
	<filename>6.jpg</filename>
	<path>/home/ironman/license-plate-recognition/Prabhu-task/hebe-task/indonesiadata_plate/data/images/train/6.jpg</path>
	<source>
		<database>Unknown</database>
	</source>
	<size>
		<width>2592</width>
		<height>1944</height>
		<depth>1</depth>
	</size>
	<segmented>0</segmented>
	<object>
		<name>plate</name>
		<pose>Unspecified</pose>
		<truncated>0</truncated>
		<difficult>0</difficult>
		<bndbox>
			<xmin>292</xmin>
			<ymin>1281</ymin>
			<xmax>669</xmax>
			<ymax>1406</ymax>
		</bndbox>
	</object>
	<object>
		<name>day_truck_front</name>
		<pose>Unspecified</pose>
		<truncated>0</truncated>
		<difficult>0</difficult>
		<bndbox>
			<xmin>7</xmin>
			<ymin>15</ymin>
			<xmax>1721</xmax>
			<ymax>1936</ymax>
		</bndbox>
	</object>
</annotation>
